pyksh-0.0.6.dist-info/METADATA
pyksh-0.0.6.dist-info/WHEEL
pyksh-0.0.6.dist-info/entry_points.txt
pyksh/shader.py
pyksh/error.py
pyksh/variables.py
pyksh/__init__.py
pyksh/cli.py
pyksh/__main__.py
pyksh/pyksh.cpython-312-darwin.so
pyksh-0.0.6.dist-info/RECORD
