Metadata-Version: 2.4
Name: pyksh
Version: 0.0.6
Classifier: Programming Language :: Rust
Classifier: Programming Language :: Python :: Implementation :: CPython
Classifier: Programming Language :: Python :: Implementation :: PyPy
Requires-Dist: pcpp>=1.30
Requires-Dist: colorama>=0.4.6
Summary: Don't Starve / Don't Stave Together shader file parser & compiler in python.
Author-email: LaoWang <wzh2021@pku.edu.cn>
License: MIT
Requires-Python: >=3.8
Project-URL: Homepage, https://github.com/lw-0x4eb1a/PyKsh/
Project-URL: Issues, https://github.com/lw-0x4eb1a/PyKsh/issues
